mdslides/Engines.py
mdslides/Utils.py
mdslides/__init__.py
mdslides/__main__.py
mdslides-0.1.5.dist-info/METADATA
mdslides-0.1.5.dist-info/WHEEL
mdslides-0.1.5.dist-info/entry_points.txt
mdslides-0.1.5.dist-info/RECORD
