Metadata-Version: 2.4
Name: mdslides
Version: 0.1.5
Summary: A tool for generating slides from markdown files using different backends.
Maintainer-email: CD Clark III <clifton.clark@gmail.com>
License-Expression: MIT
Requires-Python: >=3.10
Requires-Dist: click>=8.1.7
Requires-Dist: packaging>=24.2
Requires-Dist: requests>=2.32.3
